quantumtools/__init__.py
quantumtools/metrics.py
quantumtools-0.1.3.dist-info/METADATA
quantumtools-0.1.3.dist-info/WHEEL
quantumtools-0.1.3.dist-info/LICENSE
quantumtools-0.1.3.dist-info/RECORD
