Metadata-Version: 2.1
Name: quantumtools
Version: 0.1.3
Summary: 
License: GPL-3.0-or-later
Author: Stanley Wang
Author-email: s.wang4331@gmail.com
Requires-Python: >=3.8,<4.0
Classifier: License :: OSI Approved :: GNU General Public License v3 or later (GPLv3+)
Classifier: Programming Language :: Python :: 3
Classifier: Programming Language :: Python :: 3.8
Classifier: Programming Language :: Python :: 3.9
Classifier: Programming Language :: Python :: 3.10
Classifier: Programming Language :: Python :: 3.11
Requires-Dist: matplotlib (>=3.1.3,<4.0.0)
Requires-Dist: pandas (>=1.0.0,<2.0.0)
Requires-Dist: scikit-learn (>=1.0.0,<2.0.0)
